mongo/__init__.py
mongo/mongo.py
backwork_backup_mongo-0.3.2.dist-info/LICENSE
backwork_backup_mongo-0.3.2.dist-info/METADATA
backwork_backup_mongo-0.3.2.dist-info/WHEEL
backwork_backup_mongo-0.3.2.dist-info/entry_points.txt
backwork_backup_mongo-0.3.2.dist-info/top_level.txt
backwork_backup_mongo-0.3.2.dist-info/RECORD
