Metadata-Version: 2.1
Name: backwork-backup-mongo
Version: 0.3.2
Summary: Backwork plug-in for MongoDB backups.
Home-page: https://github.com/IBM/backwork-backup-mongo
Author: Luiz Aoqui
Author-email: laoqui@ca.ibm.com
License: Apache 2
Classifier: Development Status :: 3 - Alpha
Classifier: Environment :: Console
Classifier: Intended Audience :: Developers
Classifier: Intended Audience :: System Administrators
Classifier: Operating System :: POSIX :: Linux
Classifier: Programming Language :: Python :: 2.7
Classifier: Programming Language :: Python :: 2 :: Only
Classifier: License :: OSI Approved :: Apache Software License
Classifier: Topic :: Database
Classifier: Topic :: System :: Archiving :: Backup
Classifier: Topic :: Utilities
License-File: LICENSE
Requires-Dist: backwork
